[
 {"addr":"Q-PIVOT-MARKET","_src":"C","terminal":"question-set","loadBearing":true,"conjecture":true,"status":"imputed-decomposition","namesWithheldResolver":"DS-EARLYCASE-DEC2019","claim":"Quantitative: market/ascertainment factor F2 is the dominant single lever (~3.7 orders); neutralising F2 collapses the cross-analysis spread from ~8.2 to ~2.5 orders. Bottom-line spread sourced; per-factor decomposition imputed to fit stated posteriors.","readings":[{"side":"zoonosis-read: clustering ~1000-5000:1 for zoonosis"},{"side":"lab-read (Levin): SAME case list, no-market-link subpattern ~27:1 for lab"}],"assertedLean":null,"sources":[{"ident":"DS-EARLYCASE-DEC2019","rel":"anchor","typing":"author-declared"}]},
 {"addr":"Q-FCS-DEFUSE","_src":"C","terminal":"pending","loadBearing":false,"conjecture":true,"status":"imputed-decomposition","namesWithheldResolver":"DS-LABRECORDS-WIV","claim":"Quantitative: FCS+DEFUSE factor F4 favours lab up to ~2.5 orders, the most values-laden lab-favouring factor; execution gated on withheld WIV records.","readings":[{"side":"strong-match"},{"side":"natural-recombination, unfunded"}],"assertedLean":null,"sources":[{"ident":"DS-FCS-MOLEC","rel":"concept","typing":"author-declared"},{"ident":"DS-DEFUSE-2018","rel":"anchor","typing":"author-declared"},{"ident":"DS-LABRECORDS-WIV","rel":"conflicts-with","typing":"author-declared"}]}
]
